gloo_client/__init__.py
gloo_client/app_client.py
gloo_client/base_client.py
gloo_client/client.py
gloo_client/environment.py
gloo_client/model/__init__.py
gloo_client/model/core/__init__.py
gloo_client/model/core/datetime_utils.py
gloo_client/model/resources/__init__.py
gloo_client/model/resources/app/__init__.py
gloo_client/model/resources/app/app_list_response.py
gloo_client/model/resources/app/app_response.py
gloo_client/model/resources/app/create_app_request.py
gloo_client/model/resources/app/llm_request_params.py
gloo_client/model/resources/app/open_ai_completion_endpoint_v_1_params.py
gloo_client/model/resources/app/prompt_request.py
gloo_client/model/resources/app/prompt_response.py
gloo_client/model/resources/app/search_params.py
gloo_client/model/resources/app/search_request.py
gloo_client/model/resources/app/search_response.py
gloo_client/model/resources/app/search_result.py
gloo_client/model/resources/app/search_result_metadata.py
gloo_client/model/resources/app/update_app_request.py
gloo_client/model/resources/common/__init__.py
gloo_client/model/resources/common/embedding_type.py
gloo_client/model/resources/common/stage_type.py
gloo_client/model/resources/document/__init__.py
gloo_client/model/resources/document/create_document_request.py
gloo_client/model/resources/document/document_annotation.py
gloo_client/model/resources/document/document_content.py
gloo_client/model/resources/document/document_list_response.py
gloo_client/model/resources/document/document_query_id.py
gloo_client/model/resources/document/document_response.py
gloo_client/model/resources/document/document_response_with_content.py
gloo_client/model/resources/document/embedding_status.py
gloo_client/model/resources/document/update_document_request.py
gloo_client/model/resources/error/__init__.py
gloo_client/model/resources/error/app_not_found_body.py
gloo_client/model/resources/error/document_not_found_body.py
gloo_client/py.typed
gloo_client-1.2.0.dist-info/WHEEL
gloo_client-1.2.0.dist-info/METADATA
gloo_client-1.2.0.dist-info/RECORD
