Metadata-Version: 2.1
Name: gloo-client
Version: 1.2.0
Summary: 
Author: Vaibhav Gupta
Author-email: vbv@gloo.chat
Requires-Python: >=3.7,<4.0
Classifier: Programming Language :: Python :: 3
Classifier: Programming Language :: Python :: 3.7
Classifier: Programming Language :: Python :: 3.8
Classifier: Programming Language :: Python :: 3.9
Classifier: Programming Language :: Python :: 3.10
Classifier: Programming Language :: Python :: 3.11
Requires-Dist: pydantic (>=1.10.2,<2.0.0)
Requires-Dist: requests (>=2.28.1,<3.0.0)
Requires-Dist: types-requests (>=2.28.11.1,<3.0.0.0)
